LaRoboLiga24/__init__.py
LaRoboLiga24/envs/LaRoboLiga24.py
LaRoboLiga24/envs/__init__.py
LaRoboLiga24-0.2.0.dist-info/METADATA
LaRoboLiga24-0.2.0.dist-info/WHEEL
LaRoboLiga24-0.2.0.dist-info/top_level.txt
LaRoboLiga24-0.2.0.dist-info/RECORD
